{"commitInfo":{"timestamp":1778421102369,"operation":"STREAMING UPDATE","operationParameters":{"outputMode":"Append","queryId":"43c1129c-5cd4-452f-bc16-e5aa93fa1581","epochId":"11"},"readVersion":10,"isolationLevel":"Serializable","isBlindAppend":true,"operationMetrics":{"numRemovedFiles":"0","numOutputRows":"4000","numOutputBytes":"62560","numAddedFiles":"1"},"engineInfo":"Apache-Spark/3.5.1 Delta-Lake/3.2.0","txnId":"0362e427-ff0a-408c-bf56-905e44524c7f"}}
{"txn":{"appId":"43c1129c-5cd4-452f-bc16-e5aa93fa1581","version":11,"lastUpdated":1778421102369}}
{"add":{"path":"part-00000-12b4c2d0-0261-4eaa-923a-a85810659b5e-c000.snappy.parquet","partitionValues":{},"size":62560,"modificationTime":1778421443446,"dataChange":true,"stats":"{\"numRecords\":4000,\"minValues\":{\"userId\":166,\"movieId\":1,\"rating\":0.5,\"timestamp\":828163431,\"rating_datetime\":\"1996-03-30 05:23:51\"},\"maxValues\":{\"userId\":187,\"movieId\":204698,\"rating\":5.0,\"timestamp\":1574184136,\"rating_datetime\":\"2019-11-19 17:22:16\"},\"nullCount\":{\"userId\":0,\"movieId\":0,\"rating\":0,\"timestamp\":0,\"rating_datetime\":0}}"}}
