{"commitInfo":{"timestamp":1778421117685,"operation":"STREAMING UPDATE","operationParameters":{"outputMode":"Append","queryId":"43c1129c-5cd4-452f-bc16-e5aa93fa1581","epochId":"18"},"readVersion":17,"isolationLevel":"Serializable","isBlindAppend":true,"operationMetrics":{"numRemovedFiles":"0","numOutputRows":"1932","numOutputBytes":"33269","numAddedFiles":"1"},"engineInfo":"Apache-Spark/3.5.1 Delta-Lake/3.2.0","txnId":"e897c30b-e794-4ea8-a4ed-bd50d7ff29d5"}}
{"txn":{"appId":"43c1129c-5cd4-452f-bc16-e5aa93fa1581","version":18,"lastUpdated":1778421117684}}
{"add":{"path":"part-00000-d7f2464f-d9f3-41f1-9754-f49d3e2870fd-c000.snappy.parquet","partitionValues":{},"size":33269,"modificationTime":1778421458705,"dataChange":true,"stats":"{\"numRecords\":1932,\"minValues\":{\"userId\":281,\"movieId\":1,\"rating\":0.5,\"timestamp\":902173322,\"rating_datetime\":\"1998-08-03 19:42:02\"},\"maxValues\":{\"userId\":296,\"movieId\":204692,\"rating\":5.0,\"timestamp\":1570485096,\"rating_datetime\":\"2019-10-07 21:51:36\"},\"nullCount\":{\"userId\":0,\"movieId\":0,\"rating\":0,\"timestamp\":0,\"rating_datetime\":0}}"}}
